snowflake/Generator.py
snowflake/Snowflake.py
snowflake/__init__.py
snowflake.py-1.0.0.dist-info/LICENSE
snowflake.py-1.0.0.dist-info/METADATA
snowflake.py-1.0.0.dist-info/WHEEL
snowflake.py-1.0.0.dist-info/top_level.txt
snowflake.py-1.0.0.dist-info/RECORD
