Metadata-Version: 2.1
Name: snowflake.py
Version: 1.0.0
Summary: Simple Twitter snowflake-like id generator
Home-page: https://github.com/RoboSkyrat/snowflake.py
Author: Skyrat
Author-email: pythonProjects@skyrat.dev
License: UNKNOWN
Platform: UNKNOWN
Classifier: Programming Language :: Python :: 3
Classifier: Development Status :: 5 - Production/Stable
Classifier: License :: OSI Approved :: MIT License
Classifier: Operating System :: OS Independent
Requires-Python: >=3.6
